handofcats/__init__.py
handofcats/__main__.py
handofcats/accessor.py
handofcats/cli.py
handofcats/config.py
handofcats/customize.py
handofcats/driver.py
handofcats/injector.py
handofcats/langhelpers.py
handofcats/types.py
handofcats/actions/__init__.py
handofcats/actions/_ast.py
handofcats/actions/_codeobject.py
handofcats/actions/codegen.py
handofcats/actions/commandline.py
handofcats-3.3.0.dist-info/METADATA
handofcats-3.3.0.dist-info/WHEEL
handofcats-3.3.0.dist-info/entry_points.txt
handofcats-3.3.0.dist-info/top_level.txt
handofcats-3.3.0.dist-info/RECORD
